exceptionman/__init__.py
exceptionman/_traceback.py
exceptionman/hook.py
exceptionman/reporter_exception.py
exceptionman-0.1.0.dist-info/METADATA
exceptionman-0.1.0.dist-info/WHEEL
exceptionman-0.1.0.dist-info/top_level.txt
exceptionman-0.1.0.dist-info/RECORD
