Metadata-Version: 2.2
Name: ExceptionMan
Version: 0.1.0
Requires-Python: >=3.10
Requires-Dist: MDit<0.2,>=0.1
Requires-Dist: rich<14,>=13.5
Requires-Dist: pygments
